<Properties StartupConfiguration="{78DB5665-9DD5-45E4-9B92-795F54B02808}|Default">
  <MonoDevelop.Ide.ItemProperties.03.Validation PreferredExecutionTarget="MonoDevelop.Default" />
  <MonoDevelop.Ide.DebuggingService.PinnedWatches />
  <MonoDevelop.Ide.Workspace ActiveConfiguration="Debug" />
  <MonoDevelop.Ide.ItemProperties.02.Salary PreferredExecutionTarget="MonoDevelop.Default" />
  <MonoDevelop.Ide.ItemProperties.04.Team PreferredExecutionTarget="MonoDevelop.Default" />
  <MonoDevelop.Ide.DebuggingService.Breakpoints>
    <BreakpointStore />
  </MonoDevelop.Ide.DebuggingService.Breakpoints>
  <MultiItemStartupConfigurations />
  <MonoDevelop.Ide.ItemProperties.01.Person PreferredExecutionTarget="MonoDevelop.Default" />
  <MonoDevelop.Ide.Workbench ActiveDocument="03.Validation/Person.cs">
    <Files>
      <File FileName="03.Validation/Person.cs" Line="1" Column="1" />
      <File FileName="04.Team/Person.cs" Line="47" Column="18" />
      <File FileName="02.Salary/Person.cs" />
      <File FileName="01.Person/Person.cs" />
      <File FileName="01.Person/StartUp.cs" />
      <File FileName="02.Salary/StartUp.cs" />
      <File FileName="03.Validation/StartUp.cs" />
      <File FileName="04.Team/StartUp.cs" />
      <File FileName="04.Team/Team.cs" />
    </Files>
    <Pads>
      <Pad Id="ProjectPad">
        <State name="__root__">
          <Node name="05.Encapsulation">
            <Node name="01.Person" expanded="True" />
            <Node name="02.Salary" expanded="True" />
            <Node name="03.Validation" expanded="True">
              <Node name="Person.cs" selected="True" />
            </Node>
            <Node name="04.Team" expanded="True" />
          </Node>
        </State>
      </Pad>
      <Pad Id="MonoDevelop.Debugger.WatchPad">
        <State />
      </Pad>
    </Pads>
  </MonoDevelop.Ide.Workbench>
</Properties>