<Properties StartupConfiguration="{001EF8E1-1E9F-4BD1-AE99-FBA2EA7B34EB}|Default">
  <MonoDevelop.Ide.ItemProperties.02.AMinerTask PreferredExecutionTarget="MonoDevelop.Default" />
  <MonoDevelop.Ide.Workbench>
    <Pads>
      <Pad Id="ProjectPad">
        <State name="__root__">
          <Node name="26.AssociativeArrays-Exercise" expanded="True" />
        </State>
      </Pad>
      <Pad Id="MonoDevelop.Debugger.WatchPad">
        <State />
      </Pad>
    </Pads>
  </MonoDevelop.Ide.Workbench>
  <MonoDevelop.Ide.DebuggingService.Breakpoints />
  <MonoDevelop.Ide.ItemProperties.04.SoftUniParking FirstBuild="True" />
  <MonoDevelop.Ide.Workspace ActiveConfiguration="Debug" />
  <MultiItemStartupConfigurations />
  <MonoDevelop.Ide.DebuggingService.PinnedWatches />
  <MonoDevelop.Ide.ItemProperties.03.Orders PreferredExecutionTarget="MonoDevelop.Default" />
  <MonoDevelop.Ide.ItemProperties.01.CountCharsInAString PreferredExecutionTarget="MonoDevelop.Default" />
</Properties>